iprscan_rest/__init__.py
iprscan_rest/iprscan_rest.py
iprscan_rest-0.0.1.dist-info/METADATA
iprscan_rest-0.0.1.dist-info/RECORD
iprscan_rest-0.0.1.dist-info/WHEEL
iprscan_rest-0.0.1.dist-info/top_level.txt
