Metadata-Version: 2.1
Name: iprscan-rest
Version: 0.0.1
Summary: This package allows to query the InterProScan REST API
Home-page: UNKNOWN
Author: Damien Vantourout
Author-email: damien.vantourout@gmail.com
License: UNKNOWN
Platform: UNKNOWN
Classifier: Programming Language :: Python :: 3
Classifier: Topic :: Scientific/Engineering :: Bio-Informatics
Classifier: Operating System :: POSIX :: Linux
Classifier: License :: OSI Approved :: GNU General Public License v3 (GPLv3)
